souJpg/__init__.py
souJpg/comm/__init__.py
souJpg/comm/contextManagers.py
souJpg/comm/projectUitls.py
souJpg/comm/threadPools.py
souJpg/comm/utils.py
souJpg/comm/cfg/__init__.py
souJpg/comm/cfg/utils.py
souJpg/comm/cfg/vcgCfg.py
souJpg/comm/decorators/__init__.py
souJpg/comm/decorators/base.py
souJpg/comm/decorators/comm.py
souJpg/comm/decorators/methodRetry.py
souJpg/comm/test/__init__.py
souJpg_comm-2.0.2.dist-info/METADATA
souJpg_comm-2.0.2.dist-info/WHEEL
souJpg_comm-2.0.2.dist-info/top_level.txt
souJpg_comm-2.0.2.dist-info/RECORD
