Metadata-Version: 2.1
Name: souJpg-comm
Version: 2.0.2
Summary: souJpg-comm
Home-page: 
Author: zhaoyufei
Author-email: 
Classifier: Programming Language :: Python :: 3
Classifier: License :: OSI Approved :: MIT License
Classifier: Operating System :: OS Independent
Requires-Python: >=3.8.10
